acres-0.1.1.dist-info/METADATA
acres-0.1.1.dist-info/WHEEL
acres-0.1.1.dist-info/entry_points.txt
acres-0.1.1.dist-info/licenses/LICENSE
acres/__init__.py
acres/py.typed
acres-0.1.1.dist-info/RECORD
